mah/__init__.py
mah-0.0.1.dist-info/LICENSE
mah-0.0.1.dist-info/METADATA
mah-0.0.1.dist-info/WHEEL
mah-0.0.1.dist-info/entry_points.txt
mah-0.0.1.dist-info/top_level.txt
mah-0.0.1.dist-info/RECORD
