Metadata-Version: 2.1
Name: mah
Version: 0.0.1
Summary: mah - mpv add-on helper
License: GNU General Public License v3 (GPLv3)
Project-URL: repository, https://codeberg.org/johndovern/mlm
Keywords: mpv
License-File: LICENSE
Requires-Dist: loadconf
Requires-Dist: GitPython
